{
  "cartes":[
    {
      "id":0,
      "nom":"Champ",
      "description":"Un champ entouré de forêts idéales pour un traquenard",
      "img":"assets/images/cartes/Champ.jpg",
      "vignette":"assets/images/cartes/vignettes/Champ.jpg"
    },
    {
      "id":1,
      "nom":"A la nuit tombante",
      "description":"Embuscade à la nuit tombante",
      "img":"assets/images/cartes/Road_Plains_DayWEBP_Logo-scaled.jpg",
      "vignette":"assets/images/cartes/vignettes/Road_Plains_DayWEBP_Logo-scaled.jpg"
    },
    {
      "id":2,
      "nom":"Au croisement",
      "description":"Un croisement de route en pleine campagne",
      "img":"assets/images/cartes/Croisement.jpg",
      "vignette":"assets/images/cartes/vignettes/Croisement.jpg"
    },
    {
      "id":3,
      "nom":"Retour sur le champ",
      "description":"Le lieu d'une ancienne bataille",
      "img":"assets/images/cartes/AncienneBataille.jpg",
      "vignette":"assets/images/cartes/vignettes/AncienneBataille.jpg"
    }
  ],
  "couleurs":[
    "#FFFFFF",
    "#C0C0C0",
    "#808080",
    "#000000",
    "#FF0000",
    "#800000",
    "#FFFF00",
    "#808000",
    "#00FF00",
    "#008000",
    "#00FFFF",
    "#008080",
    "#0000FF",
    "#000080",
    "#FF00FF",
    "#800080"
  ]
}
